ezauv/__init__.py
ezauv/acceleration_state.py
ezauv/auv.py
ezauv/hardware/__init__.py
ezauv/hardware/motor_controller.py
ezauv/hardware/sensor_interface.py
ezauv/mission/__init__.py
ezauv/mission/mission.py
ezauv/mission/tasks/__init__.py
ezauv/mission/tasks/main/__init__.py
ezauv/mission/tasks/main/accelerate_vector.py
ezauv/mission/tasks/main/run_function.py
ezauv/mission/tasks/subtasks/__init__.py
ezauv/mission/tasks/subtasks/heading_pid.py
ezauv/mission/tasks/subtasks/simulate.py
ezauv/simulation/__init__.py
ezauv/simulation/animator.py
ezauv/simulation/core.py
ezauv/simulation/fake_clock.py
ezauv/simulation/fake_sensors.py
ezauv/utils/__init__.py
ezauv/utils/clock.py
ezauv/utils/inertia.py
ezauv/utils/logger.py
ezauv/utils/pid.py
ezauv-0.1.8.dist-info/METADATA
ezauv-0.1.8.dist-info/WHEEL
ezauv-0.1.8.dist-info/top_level.txt
ezauv-0.1.8.dist-info/RECORD
