Metadata-Version: 2.4
Name: ezauv
Version: 0.1.8
Summary: A library to make coding AUVs easier
Home-page: https://github.com/beaver-auv/ezauv
Author: Andre Gordon
Author-email: gordona26@bcdschool.org
Classifier: Programming Language :: Python :: 3
Classifier: License :: OSI Approved :: MIT License
Requires-Dist: gurobipy==12.0.1
Requires-Dist: numpy==2.2.3
Requires-Dist: pygame==2.6.1
Requires-Dist: scipy==1.15.2
Requires-Dist: imageio[ffmpeg]
Dynamic: author
Dynamic: author-email
Dynamic: classifier
Dynamic: description
Dynamic: description-content-type
Dynamic: home-page
Dynamic: requires-dist
Dynamic: summary
